CHANGES.rst
MANIFEST.in
README.rst
setup.py
webit/__init__.py
webit/__init__.pyc
webit/__main__.py
webit/index.html
webit/webit
webit/webit.bat
webit/webit.py
webit/webit.pyc
webit/wsgi.py
webit.egg-info/PKG-INFO
webit.egg-info/SOURCES.txt
webit.egg-info/dependency_links.txt
webit.egg-info/not-zip-safe
webit.egg-info/top_level.txt
webit/static/jquery.min.js
webit/static/style.css
webit/static/style.less
webit/static/vue.min.js