Metadata-Version: 1.1
Name: webit
Version: 0.0.3
Summary: A web tools by Python.
Home-page: https://github.com/sintrb/webit
Author: sintrb
Author-email: sintrb@gmail.com
License: Apache
Keywords: web,tools,web tools
Platform: UNKNOWN
Classifier: Intended Audience :: End Users/Desktop
Classifier: Operating System :: OS Independent
Classifier: Programming Language :: Python :: 2.7
